MANIFEST.in
README.rst
setup.py
trunserv/__init__.py
trunserv/autoreload.py
trunserv/models.py
trunserv/tests.py
trunserv/views.py
trunserv/management/__init__.py
trunserv/management/commands/__init__.py
trunserv/management/commands/trunserver.py
trunserver.egg-info/PKG-INFO
trunserver.egg-info/SOURCES.txt
trunserver.egg-info/dependency_links.txt
trunserver.egg-info/requires.txt
trunserver.egg-info/top_level.txt