Metadata-Version: 1.0
Name: trunserver
Version: 0.0.2
Summary: Twisted based Django runserver replacement.
Home-page: https://github.com/gregarmer/trunserver
Author: Gregory Armer
Author-email: greg@codelounge.org
License: MIT
Platform: UNKNOWN
Classifier: Programming Language :: Python
Classifier: License :: OSI Approved :: MIT License
Classifier: Development Status :: 4 - Beta
Classifier: Operating System :: OS Independent
Classifier: Intended Audience :: Developers
Classifier: Topic :: Internet :: WWW/HTTP :: WSGI
